watty/__init__.py
watty/api.py
watty/util.py
watty-0.1.2.dist-info/LICENSE
watty-0.1.2.dist-info/METADATA
watty-0.1.2.dist-info/WHEEL
watty-0.1.2.dist-info/top_level.txt
watty-0.1.2.dist-info/RECORD
